dane_discovery/__init__.py
dane_discovery/dane.py
dane_discovery/exceptions.py
dane_discovery/identity.py
dane_discovery/pki.py
dane_discovery/scripts/dane_discovery_authenticate_certificate.py
dane_discovery/scripts/dane_discovery_get_ca_certificates.py
dane_discovery/scripts/dane_discovery_get_certificates.py
dane_discovery-0.22.dist-info/LICENSE
dane_discovery-0.22.dist-info/METADATA
dane_discovery-0.22.dist-info/WHEEL
dane_discovery-0.22.dist-info/entry_points.txt
dane_discovery-0.22.dist-info/top_level.txt
dane_discovery-0.22.dist-info/RECORD
