Metadata-Version: 2.1
Name: dane-discovery
Version: 0.22
Summary: A library for using DANE for public key discovery.
Home-page: https://github.com/valimail/dane_discovery
Author: Ash Wilson
Author-email: ash.d.wilson@gmail.com
License: BSD
Keywords: dane tlsa dns certificate discovery
Platform: UNKNOWN
Classifier: Development Status :: 4 - Beta
Classifier: Intended Audience :: Developers
Classifier: Operating System :: MacOS :: MacOS X
Classifier: Operating System :: POSIX :: Linux
Classifier: Programming Language :: Python :: 3.6
Classifier: Programming Language :: Python :: 3.7
Classifier: Programming Language :: Python :: 3.8
Classifier: Topic :: Security
Classifier: License :: OSI Approved :: BSD License
License-File: LICENSE
Requires-Dist: dnspython (==2.2.0)
Requires-Dist: cryptography (<37,>=3)
Requires-Dist: requests (<2.28,>=2.24)
Requires-Dist: forcediphttpsadapter
